Workbook

Sheet Instructions
C3: Possible solution
C4: Setup report to generate automatically each quarter emailed to FCM
C5: Drop copy of report in the appropriate tab
C6: Have formulas setup to summarize each company
C7: Populate summary tab

Sheet Summary
A1: 2026 Net Interest Income by Company Code
A2: Paste each quarterly Kyriba report (INTEREST_INC) unchanged into its QX tab; this tab sums column F by company code.
A4: Company | B4: 1Q | C4: 2Q | D4: 3Q | E4: 4Q | F4: 2026 Total
A5: 1000 | B5: =SUMIFS('1Q'!$F:$F,'1Q'!$A:$A,"1000",'1Q'!$B:$B,"<>"&$B$29) -> 0 | C5: =SUMIFS('2Q'!$F:$F,'2Q'!$A:$A,"1000",'2Q'!$B:$B,"<>"&$B$29) -> 0 | D5: =SUMIFS('3Q'!$F:$F,'3Q'!$A:$A,"1000",'3Q'!$B:$B,"<>"&$B$29) -> 9295165.2 | E5: =SUMIFS('4Q'!$F:$F,'4Q'!$A:$A,"1000",'4Q'!$B:$B,"<>"&$B$29) -> 0 | F5: =SUM(B5:E5) -> 9295165.2
A6: 1000 INC STI | B6: =SUMIFS('1Q'!$F:$F,'1Q'!$B:$B,$B$29) -> 0 | C6: =SUMIFS('2Q'!$F:$F,'2Q'!$B:$B,$B$29) -> 0 | D6: =SUMIFS('3Q'!$F:$F,'3Q'!$B:$B,$B$29) -> 5933452.9 | E6: =SUMIFS('4Q'!$F:$F,'4Q'!$B:$B,$B$29) -> 0 | F6: =SUM(B6:E6) -> 5933452.9
A7: 1012 | B7: =SUMIFS('1Q'!$F:$F,'1Q'!$A:$A,$A7) -> 0 | C7: =SUMIFS('2Q'!$F:$F,'2Q'!$A:$A,$A7) -> 0 | D7: =SUMIFS('3Q'!$F:$F,'3Q'!$A:$A,$A7) -> 422686.17 | E7: =SUMIFS('4Q'!$F:$F,'4Q'!$A:$A,$A7) -> 0 | F7: =SUM(B7:E7) -> 422686.17
A8: 1100 | B8: =SUMIFS('1Q'!$F:$F,'1Q'!$A:$A,$A8) -> 0 | C8: =SUMIFS('2Q'!$F:$F,'2Q'!$A:$A,$A8) -> 0 | D8: =SUMIFS('3Q'!$F:$F,'3Q'!$A:$A,$A8) -> 366355.17 | E8: =SUMIFS('4Q'!$F:$F,'4Q'!$A:$A,$A8) -> 0 | F8: =SUM(B8:E8) -> 366355.17
A9: 1200 | B9: =SUMIFS('1Q'!$F:$F,'1Q'!$A:$A,$A9) -> 0 | C9: =SUMIFS('2Q'!$F:$F,'2Q'!$A:$A,$A9) -> 0 | D9: =SUMIFS('3Q'!$F:$F,'3Q'!$A:$A,$A9) -> 115705.3 | E9: =SUMIFS('4Q'!$F:$F,'4Q'!$A:$A,$A9) -> 0 | F9: =SUM(B9:E9) -> 115705.3
A10: 1400 | B10: =SUMIFS('1Q'!$F:$F,'1Q'!$A:$A,$A10) -> 0 | C10: =SUMIFS('2Q'!$F:$F,'2Q'!$A:$A,$A10) -> 0 | D10: =SUMIFS('3Q'!$F:$F,'3Q'!$A:$A,$A10) -> 184690.59 | E10: =SUMIFS('4Q'!$F:$F,'4Q'!$A:$A,$A10) -> 0 | F10: =SUM(B10:E10) -> 184690.59
A11: 1500 | B11: =SUMIFS('1Q'!$F:$F,'1Q'!$A:$A,$A11) -> 0 | C11: =SUMIFS('2Q'!$F:$F,'2Q'!$A:$A,$A11) -> 0 | D11: =SUMIFS('3Q'!$F:$F,'3Q'!$A:$A,$A11) -> 99887.06 | E11: =SUMIFS('4Q'!$F:$F,'4Q'!$A:$A,$A11) -> 0 | F11: =SUM(B11:E11) -> 99887.06
A12: 1800 | B12: =SUMIFS('1Q'!$F:$F,'1Q'!$A:$A,$A12) -> 0 | C12: =SUMIFS('2Q'!$F:$F,'2Q'!$A:$A,$A12) -> 0 | D12: =SUMIFS('3Q'!$F:$F,'3Q'!$A:$A,$A12) -> 174818.72 | E12: =SUMIFS('4Q'!$F:$F,'4Q'!$A:$A,$A12) -> 0 | F12: =SUM(B12:E12) -> 174818.72
A13: 1810 | B13: =SUMIFS('1Q'!$F:$F,'1Q'!$A:$A,$A13) -> 0 | C13: =SUMIFS('2Q'!$F:$F,'2Q'!$A:$A,$A13) -> 0 | D13: =SUMIFS('3Q'!$F:$F,'3Q'!$A:$A,$A13) -> 1844711.8 | E13: =SUMIFS('4Q'!$F:$F,'4Q'!$A:$A,$A13) -> 0 | F13: =SUM(B13:E13) -> 1844711.8
A14: 1825 | B14: =SUMIFS('1Q'!$F:$F,'1Q'!$A:$A,$A14) -> 0 | C14: =SUMIFS('2Q'!$F:$F,'2Q'!$A:$A,$A14) -> 0 | D14: =SUMIFS('3Q'!$F:$F,'3Q'!$A:$A,$A14) -> 97463.2 | E14: =SUMIFS('4Q'!$F:$F,'4Q'!$A:$A,$A14) -> 0 | F14: =SUM(B14:E14) -> 97463.2
A15: 1840 | B15: =SUMIFS('1Q'!$F:$F,'1Q'!$A:$A,$A15) -> 0 | C15: =SUMIFS('2Q'!$F:$F,'2Q'!$A:$A,$A15) -> 0 | D15: =SUMIFS('3Q'!$F:$F,'3Q'!$A:$A,$A15) -> 13505.56 | E15: =SUMIFS('4Q'!$F:$F,'4Q'!$A:$A,$A15) -> 0 | F15: =SUM(B15:E15) -> 13505.56
A16: 2200 | B16: =SUMIFS('1Q'!$F:$F,'1Q'!$A:$A,$A16) -> 0 | C16: =SUMIFS('2Q'!$F:$F,'2Q'!$A:$A,$A16) -> 0 | D16: =SUMIFS('3Q'!$F:$F,'3Q'!$A:$A,$A16) -> 624437.13 | E16: =SUMIFS('4Q'!$F:$F,'4Q'!$A:$A,$A16) -> 0 | F16: =SUM(B16:E16) -> 624437.13
A17: 2400 | B17: =SUMIFS('1Q'!$F:$F,'1Q'!$A:$A,$A17) -> 0 | C17: =SUMIFS('2Q'!$F:$F,'2Q'!$A:$A,$A17) -> 0 | D17: =SUMIFS('3Q'!$F:$F,'3Q'!$A:$A,$A17) -> 1708655.1 | E17: =SUMIFS('4Q'!$F:$F,'4Q'!$A:$A,$A17) -> 0 | F17: =SUM(B17:E17) -> 1708655.1
A18: 2500 | B18: =SUMIFS('1Q'!$F:$F,'1Q'!$A:$A,$A18) -> 0 | C18: =SUMIFS('2Q'!$F:$F,'2Q'!$A:$A,$A18) -> 0 | D18: =SUMIFS('3Q'!$F:$F,'3Q'!$A:$A,$A18) -> 2958273.5 | E18: =SUMIFS('4Q'!$F:$F,'4Q'!$A:$A,$A18) -> 0 | F18: =SUM(B18:E18) -> 2958273.5
... A22: 2900 | B22: =SUMIFS('1Q'!$F:$F,'1Q'!$A:$A,$A22) -> 0 | C22: =SUMIFS('2Q'!$F:$F,'2Q'!$A:$A,$A22) -> 0 | D22: =SUMIFS('3Q'!$F:$F,'3Q'!$A:$A,$A22) -> 1717227.6 | E22: =SUMIFS('4Q'!$F:$F,'4Q'!$A:$A,$A22) -> 0 | F22: =SUM(B22:E22) -> 1717227.6
A23: Grand Total | B23: =SUM(B5:B22) -> 0 | C23: =SUM(C5:C22) -> 0 | D23: =SUM(D5:D22) -> 25847242 | E23: =SUM(E5:E22) -> 0 | F23: =SUM(F5:F22) -> 25847242
A25: Check: tab total less summary (s/b 0) | B25: =ROUND(SUM('1Q'!$F:$F)-B23,2) -> 0 | C25: =ROUND(SUM('2Q'!$F:$F)-C23,2) -> 0 | D25: =ROUND(SUM('3Q'!$F:$F)-D23,2) -> 0 | E25: =ROUND(SUM('4Q'!$F:$F)-E23,2) -> 0
A27: Notes
A28: Company 1000 excludes the account below; that account is reported on the "1000 INC STI" line.
A29: Account split out of 1000: | B29: 1000JPMUS222
A30: A non-zero check means a tab has amounts under a company code not listed above - add a row for it.

Sheet 1Q
A1: !Q

Sheet 2Q

Sheet 3Q
A1: Report name: Cash flow ledger | E1: Template: Interest Income(INTEREST_INC)
A2: Cash flow ledger | E2: Time: 10/22/2026 - 4:32:39 PM
A3: From: 07/01/2026 to 09/30/2026 | E3: Date type: Value date
A4: Separate ledger: No: unique ledger | E4: Order by: Company/Budget code/None
A5: Amounts: In unit | E5: Currency
A6: Amount range: | E6: Reference range:
A7: Origin: All | E7: Flow status: AC
A8: Entity: Multiple
A9: Company | B9: Account | C9: Budget | D9: Value date | E9: Flow amount (currency) | F9: Flow amount (value) | G9: Description
A10: 1000 | B10: 1000JPMUS222 | C10: +INT_INC | D10: 07/01/2026 | E10: +USD | F10: 368001.46 | G10: YOUR REF=CAP OF 26/07/01,REC FROM=00000000323363792 DST ASSET MANAGER SOLUTIONS, INC. A/A/F JPM FUNDS FOR JPMORGAN 2000 CROWN COLONY DR QUINCY MA 02169-0953 US,B/O CUSTOMER=0002430/00005023346 AFLAC INCORPORATED ATTN CORPORATE TREASURY 1932 WYNNTON RD,REMARK=COLUMBUS GA 31999-0001 DEBIT REF 0129140745180107,REC GFP=07011319
A11: 1000 | B11: 1000JPMUS269 | C11: +INT_INC | D11: 07/01/2026 | E11: +USD | F11: 1023.38 | G11: REMARK=NEXT DAY INTEREST PAYMENT FROM ACCOUNT 000000550381344
A12: 1000 | B12: 1000JPMUS269 | C12: +INT_INC | D12: 07/01/2026 | E12: +USD | F12: 1552481.5 | G12: YOUR REF=NOTPROVIDED,REC FROM=00000000066001633 J.P. MORGAN SECURITIES LLC 383 MADISON AVE NEW YORK NY 10179-0001 US,B/O CUSTOMER=/7528076412 AFLAC INCORPORATED ATTN: CORPORATE FINANCE 1932 WYNNTON ROAD COLUMBUS GA31999-0002,B/O BANK=J.P. MORGAN SECURITIES LLC 383 MADISON AVENUE NEW YORK NY US,REMARK=ICD DIVIDEND /OCMT/USD1552481,51/ DEBIT REF 2607010591100001,REC GFP=07011647
A13: 1000 | B13: 1000JPMUS222 | C13: +INT_INC | D13: 07/01/2026 | E13: +USD | F13: 1034525.4 | G13: YOUR REF=NOTPROVIDED,REC FROM=00000000066001633 J.P. MORGAN SECURITIES LLC 383 MADISON AVE NEW YORK NY 10179-0001 US,B/O CUSTOMER=/7528149219 AFLAC INCORPORATED ST INVESTMENTS (AFLSTI) 1932 WYNNTON ROAD COLUMBUS GA31999-0002,B/O BANK=J.P. MORGAN SECURITIES LLC 383 MADISON AVENUE NEW YORK NY US,REMARK=ICD DIVIDEND /OCMT/USD1034525,36/ DEBIT REF 2607010601300001,REC GFP=07011652
A14: 1000 | B14: 1000JPMUS269 | C14: +INT_INC | D14: 07/01/2026 | E14: +USD | F14: 6727.33 | G14: REMARK=NEXT DAY INTEREST PAYMENT FROM ACCOUNT 000000639688222
A15: 1000 | B15: 1000JPMUS269 | C15: +INT_INC | D15: 07/01/2026 | E15: +USD | F15: 7685.55 | G15: REMARK=NEXT DAY INTEREST PAYMENT FROM ACCOUNT 000000550378878
A16: 1000 | B16: 1000JPMUS269 | C16: +INT_INC | D16: 07/01/2026 | E16: +USD | F16: 1773.65 | G16: REMARK=NEXT DAY INTEREST PAYMENT FROM ACCOUNT 000000890456759
A17: 1000 | B17: 1000JPMUS269 | C17: +INT_INC | D17: 07/01/2026 | E17: +USD | F17: 414.68 | G17: REMARK=NEXT DAY INTEREST PAYMENT FROM ACCOUNT 000000890456775
A18: 1000 | B18: 1000JPMUS269 | C18: +INT_INC | D18: 07/01/2026 | E18: +USD | F18: 1268.64 | G18: REMARK=NEXT DAY INTEREST PAYMENT FROM ACCOUNT 000000773092231
A19: 1000 | B19: 1000JPMUS269 | C19: +INT_INC | D19: 07/01/2026 | E19: +USD | F19: 1025.47 | G19: REMARK=NEXT DAY INTEREST PAYMENT FROM ACCOUNT 000000550378910
A20: 1000 | B20: 1000CITUS498 | C20: +INT_INC | D20: 07/01/2026 | E20: +USD | F20: 312609.08 | G20: FR:INTERESTENDT:20260701TRID:NONREFPY:INTEREST ON DEMAND DEPOSIT ACCOUNT AVAILABLE BALANCE
A21: 1000 | B21: 1000JPMUS269 | C21: +INT_INC | D21: 07/02/2026 | E21: +USD | F21: 17750.09 | G21: YOUR REF=NOTPROVIDED,REC FROM=00000000066001633 J.P. MORGAN SECURITIES LLC 383 MADISON AVE NEW YORK NY 10179-0001 US,B/O CUSTOMER=/7528076412 AFLAC INCORPORATED ATTN: CORPORATE FINANCE 1932 WYNNTON ROAD COLUMBUS GA31999-0002,B/O BANK=J.P. MORGAN SECURITIES LLC 383 MADISON AVENUE NEW YORK NY US,REMARK=ICD DIVIDEND /OCMT/USD17750,09/ DEBIT REF 2607020582500001,REC GFP=07022014
... A70: 1000 | B70: 1000PNCUS489 | C70: +INT_INC | D70: 09/30/2026 | E70: +USD | F70: 76002.31 | G70: INTEREST PAYMENT
B71: Company 1000 | D71: D:-USD 0 | G71: Fee.
A72: 1012 | B72: 1012JPMUS900 | C72: +INT_INC | D72: 07/01/2026 | E72: +USD | F72: 136134.72 | G72: YOUR REF=NOTPROVIDED,REC FROM=00000000066001633 J.P. MORGAN SECURITIES LLC 383 MADISON AVE NEW YORK NY 10179-0001 US,B/O CUSTOMER=/7528157618 AFLAC GI HOLDINGS LLC 1932 WYNNTON ROAD COLUMBUS GA31999-0002,B/O BANK=J.P. MORGAN SECURITIES LLC 383 MADISON AVENUE NEW YORK NY US,REMARK=ICD DIVIDEND /OCMT/USD136134,72/ DEBIT REF 2607010397400001,REC GFP=07011342
A73: 1012 | B73: 1012JPMUS900 | C73: +INT_INC | D73: 07/31/2026 | E73: +USD | F73: 877.14 | G73: REMARK=INTEREST PAYMENT
A74: 1012 | B74: 1012JPMUS900 | C74: +INT_INC | D74: 08/03/2026 | E74: +USD | F74: 141331.44 | G74: YOUR REF=NOTPROVIDED,REC FROM=00000000066001633 J.P. MORGAN SECURITIES LLC 383 MADISON AVE NEW YORK NY 10179-0001 US,B/O CUSTOMER=/7528157618 AFLAC GI HOLDINGS LLC 1932 WYNNTON ROAD COLUMBUS GA31999-0002,B/O BANK=J.P. MORGAN SECURITIES LLC 383 MADISON AVENUE NEW YORK NY US,REMARK=ICD DIVIDEND /OCMT/USD141331,44/ DEBIT REF 2608030403400001,REC GFP=08031602
A75: 1012 | B75: 1012JPMUS900 | C75: +INT_INC | D75: 08/31/2026 | E75: +USD | F75: 1131 | G75: REMARK=INTEREST PAYMENT
A76: 1012 | B76: 1012JPMUS900 | C76: +INT_INC | D76: 09/01/2026 | E76: +USD | F76: 131107.39 | G76: YOUR REF=NOTPROVIDED,REC FROM=00000000066001633 J.P. MORGAN SECURITIES LLC 383 MADISON AVE NEW YORK NY 10179-0001 US,B/O CUSTOMER=/7528157618 AFLAC GI HOLDINGS LLC 1932 WYNNTON ROAD COLUMBUS GA31999-0002,B/O BANK=J.P. MORGAN SECURITIES LLC 383 MADISON AVENUE NEW YORK NY US,REMARK=ICD DIVIDEND /OCMT/USD131107,39/ DEBIT REF 2609011721600001,REC GFP=09012013
A77: 1012 | B77: 1012JPMUS900 | C77: +INT_INC | D77: 09/02/2026 | E77: +USD | F77: 11262.75 | G77: YOUR REF=NOTPROVIDED,REC FROM=00000000066001633 J.P. MORGAN SECURITIES LLC 383 MADISON AVE NEW YORK NY 10179-0001 US,B/O CUSTOMER=/7528157618 AFLAC GI HOLDINGS LLC 1932 WYNNTON ROAD COLUMBUS GA31999-0002,B/O BANK=J.P. MORGAN SECURITIES LLC 383 MADISON AVENUE NEW YORK NY US,REMARK=ICD DIVIDEND /OCMT/USD11262,75/ DEBIT REF 2609020198300001,REC GFP=09021438
A78: 1012 | B78: 1012JPMUS900 | C78: +INT_INC | D78: 09/30/2026 | E78: +USD | F78: 841.73 | G78: REMARK=INTEREST PAYMENT
B79: Company 1012 | D79: D:-USD 0 | G79: Fee.
A80: 1100 | B80: 1100JPMUS783 | C80: +INT_INC | D80: 07/01/2026 | E80: +USD | F80: 112859.26 | G80: YOUR REF=NOTPROVIDED,REC FROM=00000000066001633 J.P. MORGAN SECURITIES LLC 383 MADISON AVE NEW YORK NY 10179-0001 US,B/O CUSTOMER=/7528076511 AFLAC INTERNATIONAL INC ATTN: CORPORATE FINANCE 1932 WYNNTON ROAD COLUMBUS GA31999-0002,B/O BANK=J.P. MORGAN SECURITIES LLC 383 MADISON AVENUE NEW YORK NY US,REMARK=ICD DIVIDEND /OCMT/USD112859,26/ DEBIT REF 2607010565000001,REC GFP=07011622
A81: 1100 | B81: 1100JPMUS783 | C81: +INT_INC | D81: 07/01/2026 | E81: +USD | F81: 110.14 | G81: REMARK=NEXT DAY INTEREST PAYMENT FROM ACCOUNT 000000773093999
A82: 1100 | B82: 1100JPMUS783 | C82: +INT_INC | D82: 07/14/2026 | E82: +USD | F82: 1701.63 | G82: YOUR REF=NOTPROVIDED,REC FROM=00000000066001633 J.P. MORGAN SECURITIES LLC 383 MADISON AVE NEW YORK NY 10179-0001 US,B/O CUSTOMER=/7528076511 AFLAC INTERNATIONAL INC ATTN: CORPORATE FINANCE 1932 WYNNTON ROAD COLUMBUS GA31999-0002,B/O BANK=J.P. MORGAN SECURITIES LLC 383 MADISON AVENUE NEW YORK NY US,REMARK=ICD DIVIDEND /OCMT/USD1701,63/ DEBIT REF 2607140577900001,REC GFP=07142112
A83: 1100 | B83: 1100JPMUS783 | C83: +INT_INC | D83: 07/14/2026 | E83: +USD | F83: 633.44 | G83: YOUR REF=NOTPROVIDED,REC FROM=00000000066001633 J.P. MORGAN SECURITIES LLC 383 MADISON AVE NEW YORK NY 10179-0001 US,B/O CUSTOMER=/7528076511 AFLAC INTERNATIONAL INC ATTN: CORPORATE FINANCE 1932 WYNNTON ROAD COLUMBUS GA31999-0002,B/O BANK=J.P. MORGAN SECURITIES LLC 383 MADISON AVENUE NEW YORK NY US,REMARK=ICD DIVIDEND /OCMT/USD633,44/ DEBIT REF 2607140241900001,REC GFP=07141512
A84: 1100 | B84: 1100JPMUS783 | C84: +INT_INC | D84: 07/14/2026 | E84: +USD | F84: 24014.3 | G84: YOUR REF=NOTPROVIDED,REC FROM=00000000066001633 J.P. MORGAN SECURITIES LLC 383 MADISON AVE NEW YORK NY 10179-0001 US,B/O CUSTOMER=/7528076511 AFLAC INTERNATIONAL INC ATTN: CORPORATE FINANCE 1932 WYNNTON ROAD COLUMBUS GA31999-0002,B/O BANK=J.P. MORGAN SECURITIES LLC 383 MADISON AVENUE NEW YORK NY US,REMARK=ICD DIVIDEND /OCMT/USD24014,3/ DEBIT REF 2607140241200001,REC GFP=07141512
A85: 1100 | B85: 1100JPMUS783 | C85: +INT_INC | D85: 07/14/2026 | E85: +USD | F85: 6053.27 | G85: YOUR REF=NOTPROVIDED,REC FROM=00000000066001633 J.P. MORGAN SECURITIES LLC 383 MADISON AVE NEW YORK NY 10179-0001 US,B/O CUSTOMER=/7528076511 AFLAC INTERNATIONAL INC ATTN: CORPORATE FINANCE 1932 WYNNTON ROAD COLUMBUS GA31999-0002,B/O BANK=J.P. MORGAN SECURITIES LLC 383 MADISON AVENUE NEW YORK NY US,REMARK=ICD DIVIDEND /OCMT/USD6053,27/ DEBIT REF 2607140574500001,REC GFP=07142112
A86: 1100 | B86: 1100JPMUS783 | C86: +INT_INC | D86: 07/31/2026 | E86: +USD | F86: 1404.27 | G86: REMARK=INTEREST PAYMENT
A87: 1100 | B87: 1100JPMUS783 | C87: +INT_INC | D87: 08/03/2026 | E87: +USD | F87: 88816.09 | G87: YOUR REF=NOTPROVIDED,REC FROM=00000000066001633 J.P. MORGAN SECURITIES LLC 383 MADISON AVE NEW YORK NY 10179-0001 US,B/O CUSTOMER=/7528076511 AFLAC INTERNATIONAL INC ATTN: CORPORATE FINANCE 1932 WYNNTON ROAD COLUMBUS GA31999-0002,B/O BANK=J.P. MORGAN SECURITIES LLC 383 MADISON AVENUE NEW YORK NY US,REMARK=ICD DIVIDEND /OCMT/USD88816,09/ DEBIT REF 2608030367600001,REC GFP=08031522
A88: 1100 | B88: 1100JPMUS783 | C88: +INT_INC | D88: 08/03/2026 | E88: +USD | F88: 228.26 | G88: REMARK=NEXT DAY INTEREST PAYMENT FROM ACCOUNT 000000773093999
A89: 1100 | B89: 1100JPMUS783 | C89: +INT_INC | D89: 08/31/2026 | E89: +USD | F89: 1828.02 | G89: REMARK=INTEREST PAYMENT
A90: 1100 | B90: 1100JPMUS783 | C90: +INT_INC | D90: 09/01/2026 | E90: +USD | F90: 120370.63 | G90: YOUR REF=NOTPROVIDED,REC FROM=00000000066001633 J.P. MORGAN SECURITIES LLC 383 MADISON AVE NEW YORK NY 10179-0001 US,B/O CUSTOMER=/7528076511 AFLAC INTERNATIONAL INC ATTN: CORPORATE FINANCE 1932 WYNNTON ROAD COLUMBUS GA31999-0002,B/O BANK=J.P. MORGAN SECURITIES LLC 383 MADISON AVENUE NEW YORK NY US,REMARK=ICD DIVIDEND /OCMT/USD120370,63/ DEBIT REF 2609011412800001,REC GFP=09011437
A91: 1100 | B91: 1100JPMUS783 | C91: +INT_INC | D91: 09/01/2026 | E91: +USD | F91: 175.56 | G91: REMARK=NEXT DAY INTEREST PAYMENT FROM ACCOUNT 000000773093999
... A95: 1100 | B95: 1100JPMUS783 | C95: +INT_INC | D95: 09/30/2026 | E95: +USD | F95: 1435.67 | G95: REMARK=INTEREST PAYMENT
B96: Company 1100 | D96: D:-USD 0 | G96: Fee.
A97: 1200 | B97: 1200JPMUS627 | C97: +INT_INC | D97: 07/01/2026 | E97: +USD | F97: 31330.35 | G97: YOUR REF=NOTPROVIDED,REC FROM=00000000066001633 J.P. MORGAN SECURITIES LLC 383 MADISON AVE NEW YORK NY 10179-0001 US,B/O CUSTOMER=/7528120319 AFLAC ASSET MANAGEMENT LLC ATTN: CORPORATE FINANCE 1932 WYNNTON ROAD COLUMBUS GA31999-0002,B/O BANK=J.P. MORGAN SECURITIES LLC 383 MADISON AVENUE NEW YORK NY US,REMARK=ICD DIVIDEND /OCMT/USD31330,35/ DEBIT REF 2607010568400001,REC GFP=07011627
A98: 1200 | B98: 1200JPMUS627 | C98: +INT_INC | D98: 07/01/2026 | E98: +USD | F98: 351.2 | G98: REMARK=NEXT DAY INTEREST PAYMENT FROM ACCOUNT 000000773091621
A99: 1200 | B99: 1200JPMUS627 | C99: +INT_INC | D99: 07/02/2026 | E99: +USD | F99: 637.33 | G99: YOUR REF=NOTPROVIDED,REC FROM=00000000066001633 J.P. MORGAN SECURITIES LLC 383 MADISON AVE NEW YORK NY 10179-0001 US,B/O CUSTOMER=/7528120319 AFLAC ASSET MANAGEMENT LLC ATTN: CORPORATE FINANCE 1932 WYNNTON ROAD COLUMBUS GA31999-0002,B/O BANK=J.P. MORGAN SECURITIES LLC 383 MADISON AVENUE NEW YORK NY US,REMARK=ICD DIVIDEND /OCMT/USD637,33/ DEBIT REF 2607020331100001,REC GFP=07021619
A100: 1200 | B100: 1200JPMUS627 | C100: +INT_INC | D100: 07/02/2026 | E100: +USD | F100: 639.37 | G100: YOUR REF=NOTPROVIDED,REC FROM=00000000066001633 J.P. MORGAN SECURITIES LLC 383 MADISON AVE NEW YORK NY 10179-0001 US,B/O CUSTOMER=/7528120319 AFLAC ASSET MANAGEMENT LLC ATTN: CORPORATE FINANCE 1932 WYNNTON ROAD COLUMBUS GA31999-0002,B/O BANK=J.P. MORGAN SECURITIES LLC 383 MADISON AVENUE NEW YORK NY US,REMARK=ICD DIVIDEND /OCMT/USD639,37/ DEBIT REF 2607020330700001,REC GFP=07021619
A101: 1200 | B101: 1200JPMUS627 | C101: +INT_INC | D101: 07/31/2026 | E101: +USD | F101: 5010.07 | G101: REMARK=INTEREST PAYMENT
A102: 1200 | B102: 1200JPMUS627 | C102: +INT_INC | D102: 08/03/2026 | E102: +USD | F102: 37638.88 | G102: YOUR REF=NOTPROVIDED,REC FROM=00000000066001633 J.P. MORGAN SECURITIES LLC 383 MADISON AVE NEW YORK NY 10179-0001 US,B/O CUSTOMER=/7528120319 AFLAC ASSET MANAGEMENT LLC ATTN: CORPORATE FINANCE 1932 WYNNTON ROAD COLUMBUS GA31999-0002,B/O BANK=J.P. MORGAN SECURITIES LLC 383 MADISON AVENUE NEW YORK NY US,REMARK=ICD DIVIDEND /OCMT/USD37638,88/ DEBIT REF 2608030378100001,REC GFP=08031532
A103: 1200 | B103: 1200JPMUS627 | C103: +INT_INC | D103: 08/03/2026 | E103: +USD | F103: 446.01 | G103: REMARK=NEXT DAY INTEREST PAYMENT FROM ACCOUNT 000000773091621
A104: 1200 | B104: 1200JPMUS627 | C104: +INT_INC | D104: 08/31/2026 | E104: +USD | F104: 3851.1 | G104: REMARK=INTEREST PAYMENT
A105: 1200 | B105: 1200JPMUS627 | C105: +INT_INC | D105: 09/01/2026 | E105: +USD | F105: 514.93 | G105: REMARK=NEXT DAY INTEREST PAYMENT FROM ACCOUNT 000000773091621
A106: 1200 | B106: 1200JPMUS627 | C106: +INT_INC | D106: 09/01/2026 | E106: +USD | F106: 30957.13 | G106: YOUR REF=NOTPROVIDED,REC FROM=00000000066001633 J.P. MORGAN SECURITIES LLC 383 MADISON AVE NEW YORK NY 10179-0001 US,B/O CUSTOMER=/7528120319 AFLAC ASSET MANAGEMENT LLC ATTN: CORPORATE FINANCE 1932 WYNNTON ROAD COLUMBUS GA31999-0002,B/O BANK=J.P. MORGAN SECURITIES LLC 383 MADISON AVENUE NEW YORK NY US,REMARK=ICD DIVIDEND /OCMT/USD30957,13/ DEBIT REF 2609011421100001,REC GFP=09011442
A107: 1200 | B107: 1200JPMUS627 | C107: +INT_INC | D107: 09/30/2026 | E107: +USD | F107: 4328.93 | G107: REMARK=INTEREST PAYMENT
B108: Company 1200 | D108: D:-USD 0 | G108: Fee.
A109: 1400 | B109: 1400JPMUS809 | C109: +INT_INC | D109: 07/01/2026 | E109: +USD | F109: 57001.66 | G109: YOUR REF=NOTPROVIDED,REC FROM=00000000066001633 J.P. MORGAN SECURITIES LLC 383 MADISON AVE NEW YORK NY 10179-0001 US,B/O CUSTOMER=/7528076818 AFLAC INFORMATION TECHNOLOGY ATTN: CORPORATE FINANCE 1932 WYNNTON ROAD COLUMBUS GA31999-0002,B/O BANK=J.P. MORGAN SECURITIES LLC 383 MADISON AVENUE NEW YORK NY US,REMARK=ICD DIVIDEND /OCMT/USD57001,66/ DEBIT REF 2607010566200001,REC GFP=07011622
A110: 1400 | B110: 1400JPMUS809 | C110: +INT_INC | D110: 07/02/2026 | E110: +USD | F110: 373.73 | G110: YOUR REF=NOTPROVIDED,REC FROM=00000000066001633 J.P. MORGAN SECURITIES LLC 383 MADISON AVE NEW YORK NY 10179-0001 US,B/O CUSTOMER=/7528076818 AFLAC INFORMATION TECHNOLOGY ATTN: CORPORATE FINANCE 1932 WYNNTON ROAD COLUMBUS GA31999-0002,B/O BANK=J.P. MORGAN SECURITIES LLC 383 MADISON AVENUE NEW YORK NY US,REMARK=ICD DIVIDEND /OCMT/USD373,73/ DEBIT REF 2607020523700001,REC GFP=07021914
A111: 1400 | B111: 1400JPMUS809 | C111: +INT_INC | D111: 07/31/2026 | E111: +USD | F111: 1230 | G111: REMARK=INTEREST PAYMENT
A112: 1400 | B112: 1400JPMUS809 | C112: +INT_INC | D112: 08/03/2026 | E112: +USD | F112: 60718.11 | G112: YOUR REF=NOTPROVIDED,REC FROM=00000000066001633 J.P. MORGAN SECURITIES LLC 383 MADISON AVE NEW YORK NY 10179-0001 US,B/O CUSTOMER=/7528076818 AFLAC INFORMATION TECHNOLOGY ATTN: CORPORATE FINANCE 1932 WYNNTON ROAD COLUMBUS GA31999-0002,B/O BANK=J.P. MORGAN SECURITIES LLC 383 MADISON AVENUE NEW YORK NY US,REMARK=ICD DIVIDEND /OCMT/USD60718,11/ DEBIT REF 2608030370200001,REC GFP=08031527
A113: 1400 | B113: 1400JPMUS809 | C113: +INT_INC | D113: 08/24/2026 | E113: +USD | F113: 1359.04 | G113: YOUR REF=NOTPROVIDED,REC FROM=00000000066001633 J.P. MORGAN SECURITIES LLC 383 MADISON AVE NEW YORK NY 10179-0001 US,B/O CUSTOMER=/7528076818 AFLAC INFORMATION TECHNOLOGY ATTN: CORPORATE FINANCE 1932 WYNNTON ROAD COLUMBUS GA31999-0002,B/O BANK=J.P. MORGAN SECURITIES LLC 383 MADISON AVENUE NEW YORK NY US,REMARK=ICD DIVIDEND /OCMT/USD1359,04/ DEBIT REF 2608240241000001,REC GFP=08241532
A114: 1400 | B114: 1400JPMUS809 | C114: +INT_INC | D114: 08/31/2026 | E114: +USD | F114: 1492.76 | G114: REMARK=INTEREST PAYMENT
A115: 1400 | B115: 1400JPMUS809 | C115: +INT_INC | D115: 09/01/2026 | E115: +USD | F115: 61171.43 | G115: YOUR REF=NOTPROVIDED,REC FROM=00000000066001633 J.P. MORGAN SECURITIES LLC 383 MADISON AVE NEW YORK NY 10179-0001 US,B/O CUSTOMER=/7528076818 AFLAC INFORMATION TECHNOLOGY ATTN: CORPORATE FINANCE 1932 WYNNTON ROAD COLUMBUS GA31999-0002,B/O BANK=J.P. MORGAN SECURITIES LLC 383 MADISON AVENUE NEW YORK NY US,REMARK=ICD DIVIDEND /OCMT/USD61171,43/ DEBIT REF 2609011414300001,REC GFP=09011437
A116: 1400 | B116: 1400JPMUS809 | C116: +INT_INC | D116: 09/30/2026 | E116: +USD | F116: 1343.86 | G116: REMARK=INTEREST PAYMENT
B117: Company 1400 | D117: D:-USD 0 | G117: Fee.
A118: 1500 | B118: 1500JPMUS737 | C118: +INT_INC | D118: 07/01/2026 | E118: +USD | F118: 512.04 | G118: REMARK=NEXT DAY INTEREST PAYMENT FROM ACCOUNT 000000496584249
A119: 1500 | B119: 1500JPMUS737 | C119: +INT_INC | D119: 07/01/2026 | E119: +USD | F119: 30772.25 | G119: YOUR REF=NOTPROVIDED,REC FROM=00000000066001633 J.P. MORGAN SECURITIES LLC 383 MADISON AVE NEW YORK NY 10179-0001 US,B/O CUSTOMER=/7528135515 AFLAC BENEFITS ADVISORS CORPORATE FINANCE 1932 WYNNTON ROAD COLUMBUS GA31999-0002,B/OBANK=J.P. MORGAN SECURITIES LLC 383 MADISON AVENUE NEW YORK NY US,REMARK=ICD DIVIDEND /OCMT/USD30772,25/ DEBIT REF 2607010570200001,REC GFP=07011627
A120: 1500 | B120: 1500JPMUS737 | C120: +INT_INC | D120: 07/31/2026 | E120: +USD | F120: 1169.24 | G120: REMARK=INTEREST PAYMENT
A121: 1500 | B121: 1500JPMUS737 | C121: +INT_INC | D121: 08/03/2026 | E121: +USD | F121: 31882.91 | G121: YOUR REF=NOTPROVIDED,REC FROM=00000000066001633 J.P. MORGAN SECURITIES LLC 383 MADISON AVE NEW YORK NY 10179-0001 US,B/O CUSTOMER=/7528135515 AFLAC BENEFITS ADVISORS CORPORATE FINANCE 1932 WYNNTON ROAD COLUMBUS GA31999-0002,B/OBANK=J.P. MORGAN SECURITIES LLC 383 MADISON AVENUE NEW YORK NY US,REMARK=ICD DIVIDEND /OCMT/USD31882,91/ DEBIT REF 2608030387200001,REC GFP=08031542
A122: 1500 | B122: 1500JPMUS737 | C122: +INT_INC | D122: 08/03/2026 | E122: +USD | F122: 540.89 | G122: REMARK=NEXT DAY INTEREST PAYMENT FROM ACCOUNT 000000496584249
A123: 1500 | B123: 1500JPMUS737 | C123: +INT_INC | D123: 08/31/2026 | E123: +USD | F123: 1057.72 | G123: REMARK=INTEREST PAYMENT
A124: 1500 | B124: 1500JPMUS737 | C124: +INT_INC | D124: 09/01/2026 | E124: +USD | F124: 32339.96 | G124: YOUR REF=NOTPROVIDED,REC FROM=00000000066001633 J.P. MORGAN SECURITIES LLC 383 MADISON AVE NEW YORK NY 10179-0001 US,B/O CUSTOMER=/7528135515 AFLAC BENEFITS ADVISORS CORPORATE FINANCE 1932 WYNNTON ROAD COLUMBUS GA31999-0002,B/OBANK=J.P. MORGAN SECURITIES LLC 383 MADISON AVENUE NEW YORK NY US,REMARK=ICD DIVIDEND /OCMT/USD32339,96/ DEBIT REF 2609011425300001,REC GFP=09011447
A125: 1500 | B125: 1500JPMUS737 | C125: +INT_INC | D125: 09/01/2026 | E125: +USD | F125: 545.91 | G125: REMARK=NEXT DAY INTEREST PAYMENT FROM ACCOUNT 000000496584249
A126: 1500 | B126: 1500JPMUS737 | C126: +INT_INC | D126: 09/30/2026 | E126: +USD | F126: 1066.14 | G126: REMARK=INTEREST PAYMENT
B127: Company 1500 | D127: D:-USD 0 | G127: Fee.
A128: 1800 | B128: 1800BOAUS790 | C128: +INT_INC | D128: 07/01/2026 | E128: +USD | F128: 56889 | G128: WIRE TYPE:WIRE IN DATE:070126 TIME:1023 ETTRN:2026070100403206 SNDR REF:2212398182JSSERVICE REF:20260701MMQFMP2K024695RELATED REF:ORIG:AFLAC GLOBAL VENTURES LLC 1932 WYNNTON ROAD COLUMBUSGA31999- 0002 ID:7528180511ORG BK:J.P. MORGAN SECURITIES LLC ID:BEARUS33INS BK: ID:SND BK:JPMORGAN CHASE BANK NA ID:021000021BNF:AFLAC GLOBAL VENTURES LLC 1932 WYNNTON ROAD COLUMBUSGA31999- 0002 ID:385015897790BNF BK: ID:PAYMENT DETAILS:ICD DIVIDEND /CATPURP/CTRC /LOCINS/CTRC /INS/BEARUS33 /INS/J.P. MORGAN SECURITIES LLCUETR:a21893b0-7f59-490f-aa05-9770dbe62c67
A129: 1800 | B129: 1800BOAUS790 | C129: +INT_INC | D129: 08/03/2026 | E129: +USD | F129: 58893.87 | G129: WIRE TYPE:WIRE IN DATE:080326 TIME:1218 ETTRN:2026080300582348 SNDR REF:2280588215JSSERVICE REF:20260803MMQFMP2M029659RELATED REF:ORIG:AFLAC GLOBAL VENTURES LLC 1932 WYNNTON ROAD COLUMBUSGA31999- 0002 ID:7528180511ORG BK:J.P. MORGAN SECURITIES LLC ID:BEARUS33INS BK: ID:SND BK:JPMORGAN CHASE BANK N.A. ID:021000021BNF:AFLAC GLOBAL VENTURES LLC 1932 WYNNTON ROAD COLUMBUSGA31999- 0002 ID:385015897790BNF BK: ID:PAYMENT DETAILS:ICD DIVIDEND /CATPURP/CTRC /LOCINS/CTRC /INS/BEARUS33 /INS/J.P. MORGAN SECURITIES LLCUETR:49a1784e-7f60-4930-aa84-a7df4083952f
A130: 1800 | B130: 1800BOAUS790 | C130: +INT_INC | D130: 09/01/2026 | E130: +USD | F130: 59035.85 | G130: WIRE TYPE:WIRE IN DATE:090126 TIME:1108 ETTRN:2026090100432133 SNDR REF:2248141244JSSERVICE REF:20260901MMQFMP2L049803RELATED REF:ORIG:AFLAC GLOBAL VENTURES LLC 1932 WYNNTON ROAD COLUMBUSGA31999- 0002 ID:7528180511ORG BK:J.P. MORGAN SECURITIES LLC ID:BEARUS33INS BK: ID:SND BK:JPMORGAN CHASE BANK N.A. ID:021000021BNF:AFLAC GLOBAL VENTURES LLC 1932 WYNNTON ROAD COLUMBUSGA31999- 0002 ID:385015897790BNF BK: ID:PAYMENT DETAILS:ICD DIVIDEND /CATPURP/CTRC /LOCINS/CTRC /INS/BEARUS33 /INS/J.P. MORGAN SECURITIES LLCUETR:1c99268e-7f66-494d-bd4c-c93f8da301ce
B131: Company 1800 | D131: D:-USD 0 | G131: Fee.
A132: 1810 | B132: 1810BOAUS800 | C132: +INT_INC | D132: 07/01/2026 | E132: +USD | F132: 597661.69 | G132: WIRE TYPE:WIRE IN DATE:070126 TIME:1109 ETTRN:2026070100429324 SNDR REF:2226081182JSSERVICE REF:20260701MMQFMP2K027743RELATED REF:ORIG:AFLAC VENTURES LLC ATTN: CORPORATE FINANCE 1932WYNNTO N ROAD COLUMBUS GA31999-0002 ID:7528120418ORG BK:J.P. MORGAN SECURITIES LLC ID:BEARUS33INS BK: ID:SND BK:JPMORGAN CHASE BANK NA ID:021000021BNF:AFLAC VENTURES LLC ATTN: CORPORATE FINANCE 1932 WYNNTON ROAD COLUMBUS GA31999-0002 ID:385015897800BNF BK: ID:PAYMENT DETAILS:ICD DIVIDEND /CATPURP/CTRC /LOCINS/CTRC /INS/BEARUS33 /INS/J.P. MORGAN SECURITIES LLCUETR:a3bf63f6-7f59-490f-850a-7804aaed849f
A133: 1810 | B133: 1810BOAUS800 | C133: +INT_INC | D133: 08/03/2026 | E133: +USD | F133: 622004.34 | G133: WIRE TYPE:WIRE IN DATE:080326 TIME:1213 ETTRN:2026080300579254 SNDR REF:2269771215JSSERVICE REF:20260803MMQFMP2M029404RELATED REF:ORIG:AFLAC VENTURES LLC ATTN: CORPORATE FINANCE 1932WYNNTO N ROAD COLUMBUS GA31999-0002 ID:7528120418ORG BK:J.P. MORGAN SECURITIES LLC ID:BEARUS33INS BK: ID:SND BK:JPMORGAN CHASE BANK N.A. ID:021000021BNF:AFLAC VENTURES LLC ATTN: CORPORATE FINANCE 1932 WYNNTON ROAD COLUMBUS GA31999-0002 ID:385015897800BNF BK: ID:PAYMENT DETAILS:ICD DIVIDEND /CATPURP/CTRC /LOCINS/CTRC /INS/BEARUS33 /INS/J.P. MORGAN SECURITIES LLCUETR:4976266c-7f60-4930-960c-24bdeb733b24
A134: 1810 | B134: 1810BOAUS800 | C134: +INT_INC | D134: 09/01/2026 | E134: +USD | F134: 625045.76 | G134: WIRE TYPE:WIRE IN DATE:090126 TIME:1203 ETTRN:2026090100464549 SNDR REF:2253964244JSSERVICE REF:20260901MMQFMP2L055233RELATED REF:ORIG:AFLAC VENTURES LLC ATTN: CORPORATE FINANCE 1932WYNNTO N ROAD COLUMBUS GA31999-0002 ID:7528120418ORG BK:J.P. MORGAN SECURITIES LLC ID:BEARUS33INS BK: ID:SND BK:JPMORGAN CHASE BANK N.A. ID:021000021BNF:AFLAC VENTURES LLC ATTN: CORPORATE FINANCE 1932 WYNNTON ROAD COLUMBUS GA31999-0002 ID:385015897800BNF BK: ID:PAYMENT DETAILS:ICD DIVIDEND /CATPURP/CTRC /LOCINS/CTRC /INS/BEARUS33 /INS/J.P. MORGAN SECURITIES LLCUETR:1e7e7f30-7f66-494d-8a2a-c77e02396467
B135: Company 1810 | D135: D:-USD 0 | G135: Fee.
A136: 1825 | B136: 1825JPMUS952 | C136: +INT_INC | D136: 07/01/2026 | E136: +USD | F136: 30246.23 | G136: YOUR REF=NOTPROVIDED,REC FROM=00000000066001633 J.P. MORGAN SECURITIES LLC 383 MADISON AVE NEW YORK NY 10179-0001 US,B/O CUSTOMER=/7528165116 AFLAC VENTURES INDIA FUND LLC 1932 WYNNTON ROAD COLUMBUS GA31999-0002,B/O BANK=J.P. MORGAN SECURITIES LLC 383 MADISON AVENUE NEW YORK NY US,REMARK=ICD DIVIDEND /OCMT/USD30246,23/ DEBIT REF 2607010429000001,REC GFP=07011417
A137: 1825 | B137: 1825JPMUS952 | C137: +INT_INC | D137: 07/31/2026 | E137: +USD | F137: 1472.7 | G137: REMARK=INTEREST PAYMENT
A138: 1825 | B138: 1825JPMUS952 | C138: +INT_INC | D138: 08/03/2026 | E138: +USD | F138: 31255.23 | G138: YOUR REF=NOTPROVIDED,REC FROM=00000000066001633 J.P. MORGAN SECURITIES LLC 383 MADISON AVE NEW YORK NY 10179-0001 US,B/O CUSTOMER=/7528165116 AFLAC VENTURES INDIA FUND LLC 1932 WYNNTON ROAD COLUMBUS GA31999-0002,B/O BANK=J.P. MORGAN SECURITIES LLC 383 MADISON AVENUE NEW YORK NY US,REMARK=ICD DIVIDEND /OCMT/USD31255,23/ DEBIT REF 2608030412400001,REC GFP=08031612
A139: 1825 | B139: 1825JPMUS952 | C139: +INT_INC | D139: 08/31/2026 | E139: +USD | F139: 1535.38 | G139: REMARK=INTEREST PAYMENT
A140: 1825 | B140: 1825JPMUS952 | C140: +INT_INC | D140: 09/01/2026 | E140: +USD | F140: 31399.16 | G140: YOUR REF=NOTPROVIDED,REC FROM=00000000066001633 J.P. MORGAN SECURITIES LLC 383 MADISON AVE NEW YORK NY 10179-0001 US,B/O CUSTOMER=/7528165116 AFLAC VENTURES INDIA FUND LLC 1932 WYNNTON ROAD COLUMBUS GA31999-0002,B/O BANK=J.P. MORGAN SECURITIES LLC 383 MADISON AVENUE NEW YORK NY US,REMARK=ICD DIVIDEND /OCMT/USD31399,16/ DEBIT REF 2609011437800001,REC GFP=09011502
A141: 1825 | B141: 1825JPMUS952 | C141: +INT_INC | D141: 09/30/2026 | E141: +USD | F141: 1554.5 | G141: REMARK=INTEREST PAYMENT
B142: Company 1825 | D142: D:-USD 0 | G142: Fee.
A143: 1840 | B143: 1840JPMUS385 | C143: +INT_INC | D143: 07/01/2026 | E143: +USD | F143: 103.83 | G143: REMARK=NEXT DAY INTEREST PAYMENT FROM ACCOUNT 000000780696966
A144: 1840 | B144: 1840JPMUS385 | C144: +INT_INC | D144: 07/31/2026 | E144: +USD | F144: 4439.56 | G144: REMARK=INTEREST PAYMENT
A145: 1840 | B145: 1840JPMUS385 | C145: +INT_INC | D145: 08/03/2026 | E145: +USD | F145: 104.52 | G145: REMARK=NEXT DAY INTEREST PAYMENT FROM ACCOUNT 000000780696966
A146: 1840 | B146: 1840JPMUS385 | C146: +INT_INC | D146: 08/31/2026 | E146: +USD | F146: 4396.31 | G146: REMARK=INTEREST PAYMENT
A147: 1840 | B147: 1840JPMUS385 | C147: +INT_INC | D147: 09/01/2026 | E147: +USD | F147: 108.91 | G147: REMARK=NEXT DAY INTEREST PAYMENT FROM ACCOUNT 000000780696966
A148: 1840 | B148: 1840JPMUS385 | C148: +INT_INC | D148: 09/30/2026 | E148: +USD | F148: 4352.43 | G148: REMARK=INTEREST PAYMENT
B149: Company 1840 | D149: D:-USD 0 | G149: Fee.
A150: 2200 | B150: 2200JPMUS916 | C150: +INT_INC | D150: 07/01/2026 | E150: +USD | F150: 435.06 | G150: REMARK=NEXT DAY INTEREST PAYMENT FROM ACCOUNT 000000773095770
A151: 2200 | B151: 2200JPMUS916 | C151: +INT_INC | D151: 07/01/2026 | E151: +USD | F151: 13154.61 | G151: REMARK=NEXT DAY INTEREST PAYMENT FROM ACCOUNT 000000701872100
...

Sheet 4Q
